pipelight/__init__.py
pipelight/__main__.py
pipelight/cli.py
pipelight/gitlab_api.py
pipelight/govee_api.py
pipelight/utils.py
pipelight-0.1.0.dist-info/METADATA
pipelight-0.1.0.dist-info/WHEEL
pipelight-0.1.0.dist-info/entry_points.txt
pipelight-0.1.0.dist-info/top_level.txt
pipelight-0.1.0.dist-info/RECORD
